mcp_server_bing/__init__.py
mcp_server_bing/server.py
mseep_mcp_server_bing-0.1.3.dist-info/licenses/LICENSE
mseep_mcp_server_bing-0.1.3.dist-info/METADATA
mseep_mcp_server_bing-0.1.3.dist-info/WHEEL
mseep_mcp_server_bing-0.1.3.dist-info/top_level.txt
mseep_mcp_server_bing-0.1.3.dist-info/RECORD
